flexout/__init__.py
flexout/_version.py
flexout/base.py
flexout/csv.py
flexout/excel.py
flexout/filemgr.py
flexout/flexout.py
flexout/noop.py
flexout/tabulate.py
flexout-0.2.4.dist-info/LICENSE.txt
flexout-0.2.4.dist-info/METADATA
flexout-0.2.4.dist-info/WHEEL
flexout-0.2.4.dist-info/top_level.txt
flexout-0.2.4.dist-info/RECORD
